{
  "site": {
    "name": "Lumo AI Agency",
    "domain": "lumoaiagency.com",
    "language": "en-US"
  },
  "contact": {
    "email": "hello@lumoaiagency.com",
    "phone": "+1-512-800-0100",
    "address": "Austin, TX, USA",
    "city": "Austin"
  },
  "brand": {
    "primary_color": "#B3FF00",
    "secondary_color": "#0D0D14"
  },
  "business": {
    "niche": "marketing-agency",
    "schema_type": "MarketingAgency",
    "is_local": true,
    "founded_year": 2023,
    "target_city": "Austin",
    "target_state": "TX",
    "target_country": "US",
    "team_size": 12,
    "rating": 4.9,
    "review_count": 47
  },
  "autodetect_niche": true,
  "thresholds": {
    "word_count": [
      800,
      2500
    ],
    "faq_count": 5,
    "h2_count": [
      3,
      14
    ],
    "image_count": [
      2,
      15
    ],
    "meta_desc_length": [
      120,
      165
    ],
    "images_min": 1
  },
  "keywords": {
    "primary": "ai marketing agency",
    "secondary": [
      "ai marketing company",
      "ai marketing services"
    ],
    "supporting": [
      "digital marketing",
      "online marketing",
      "marketing strategy"
    ],
    "density_primary": [
      0.5,
      2.5
    ],
    "density_secondary": [
      0.3,
      1.2
    ]
  },
  "rules": {
    "required_schemas": [
      "Organization",
      "Service",
      "FAQPage",
      "BreadcrumbList"
    ],
    "required_mentions_in_h1_or_first_paragraph": [
      "Lumo"
    ],
    "no_cross_link_domains": [],
    "no_fake_urgency_phrases": []
  },
  "niche_overrides": {
    "niche": "marketing-agency",
    "schema_type": "Organization",
    "is_local": true,
    "required_schemas": [
      "Organization",
      "FAQPage",
      "BreadcrumbList"
    ],
    "required_cta_types": [
      "contact_form",
      "consultation",
      "phone"
    ],
    "required_trust_signals": [
      "testimonials",
      "case_studies",
      "client_logos",
      "team"
    ],
    "psychology_focus": [
      "authority",
      "social_proof",
      "trust"
    ],
    "forbidden_psychology": [
      "fake_scarcity",
      "fake_countdown",
      "false_urgency"
    ]
  }
}